PyIpsm/__init__.py
PyIpsm/ipsm.py
PyIpsm/sample_prosper.py
pyipsm-0.0.3.dist-info/METADATA
pyipsm-0.0.3.dist-info/WHEEL
pyipsm-0.0.3.dist-info/licenses/LICENSE
pyipsm-0.0.3.dist-info/RECORD
