Metadata-Version: 2.1
Name: PyIpsm
Version: 0.0.3
Summary: PyIpsm is a python package to communicate with Petroleum Experts(Petex) software - Prosper, MBAL and GAP - through openserver using Python. This Python package eliminates the the need for writing VBA code to interface with Petex software.
Project-URL: Homepage, https://github.com/kuriankattukaren/PyIpsm
Project-URL: Bug Tracker, https://github.com/kuriankattukaren/PyIpsm/issues
Author-email: Kurian Joseph Kattukaren <kuriankattukaren@gmail.com>
License-File: LICENSE
Classifier: License :: OSI Approved :: MIT License
Classifier: Operating System :: OS Independent
Classifier: Programming Language :: Python :: 3
Requires-Python: >=3.9
